{
  "todos": [
    {
      "subject": "test1",
      "completed": false,
      "body": "test1",
      "id": 1
    },
    {
      "subject": "test2",
      "completed": false,
      "body": "test2",
      "id": 2
    },
    {
      "subject": "test3",
      "completed": false,
      "body": "test3",
      "id": 3
    },
    {
      "subject": "test4",
      "completed": false,
      "body": "test4",
      "id": 4
    },
    {
      "subject": "test5",
      "completed": false,
      "body": "test5",
      "id": 5
    },
    {
      "subject": "test6",
      "completed": false,
      "body": "test6",
      "id": 6
    },
    {
      "subject": "test7",
      "completed": false,
      "body": "test7",
      "id": 7
    },
    {
      "subject": "test8",
      "completed": false,
      "body": "test8",
      "id": 8
    },
    {
      "subject": "test9",
      "completed": false,
      "body": "test9",
      "id": 9
    },
    {
      "subject": "test10",
      "completed": false,
      "body": "test10",
      "id": 10
    },
    {
      "subject": "test11",
      "completed": false,
      "body": "test11",
      "id": 11
    }
  ]
}